<monster name="Behemoth" nameDescription="a behemoth" experience="2500" speed="340" manacost="0">
	<health now="4000" max="4000" />
	<look type="0" head="0" body="0" legs="0" feet="0" addons="0" mount="0" corpse="0" />
	<targetchange interval="2000" chance="0" />
	<flags>
		<flag attackable="1" />
		<flag hostile="1" />
		<flag summonable="0" />
		<flag convinceable="0" />
		<flag illusionable="0" />
		<flag isboss="0" />
		<flag pushable="0" />
		<flag canpushitems="1" />
		<flag canpushcreatures="1" />
		<flag staticattack="90" />
		<flag targetdistance="1" />
		<flag healthHidden="0" />
		<flag canWalkOnEnergy="0" />
		<flag canWalkOnFire="1" />
		<flag canWalkOnPoison="1" />
	</flags>
	<immunities>
		<immunity paralyze="1" />
		<immunity outfit="0" />
		<immunity invisible="1" />
		<immunity drunk="0" />
		<immunity bleed="0" />
	</immunities>
	<elements>
		<element physicalPercent="10" />
		<element EnergyPercent="10" />
		<element earthPercent="80" />
		<element firePercent="30" />
		<element lifedrainPercent="0" />
		<element manadrainPercent="0" />
		<element drownPercent="0" />
		<element icePercent="-10" />
		<element holyPercent="30" />
		<element deathPercent="-5" />
	</elements>
	<attacks>
		<attack name="melee" interval="2000" chance="100" min="0" max="-455" />
	</attacks>
	<defenses armor="50" defense="50">
		<defense name="speed" interval="2000" chance="15" minspeedchange="300" maxspeedchange="300" duration="7000">
			<attribute key="areaEffect" value="redshimmer" />
		</defense>
	</defenses>
	<voices interval="5000" chance="10">
		<voice sentence="Crush the intruders!" yell="false" />
		<voice sentence="You're so little!" yell="false" />
		<voice sentence="Human flesh -  delicious!" yell="false" />
	</voices>
	<loot>
		<item id="gold coin" chance="100000" countmax="200" />
		<item id="platinum coin" chance="60301" countmax="5" />
		<item id="meat" chance="29755" />
		<item id="battle stone" chance="14985" />
		<item id="double axe" chance="10038" />
		<item id="assassin star" chance="9999" countmax="5" />
		<item id="small amethyst" chance="6089" countmax="5" />
		<item id="two handed sword" chance="6023" />
		<item id="great health potion" chance="5078" />
		<item id="dark armor" chance="4187" />
		<item id="plate armor" chance="4100" />
		<item id="crystal necklace" chance="2537" />
		<item id="perfect behemoth fang" chance="992" />
		<item id="giant sword" chance="960" />
		<item id="strange symbol" chance="832" />
		<item id="big bone" chance="706" />
		<item id="pick" chance="626" />
		<item id="behemoth claw" chance="461" />
		<item id="steel boots" chance="435" />
		<item id="crowbar" chance="128" />
		<item id="behemoth trophy" chance="117" />
		<item id="amphora" chance="101" />
		<item id="titan axe" chance="78" />
		<item id="war axe" chance="71" />
		<item id="gold coin" chance="6772" countmax="133" />
		<item id="platinum coin" chance="3222" countmax="4" />
		<item id="meat" chance="2493" />
		<item id="assassin star" chance="827" countmax="2" />
		<item id="double axe" chance="406" />
		<item id="battle stone" chance="403" />
		<item id="small amethyst" chance="335" countmax="2" />
		<item id="two handed sword" chance="323" />
		<item id="dark armor" chance="206" />
		<item id="plate armor" chance="133" />
		<item id="perfect behemoth fang" chance="112" />
		<item id="giant sword" chance="94" />
		<item id="strange symbol" chance="78" />
		<item id="great health potion" chance="69" />
		<item id="crystal necklace" chance="41" />
		<item id="pick" chance="41" />
		<item id="steel boots" chance="37" />
		<item id="big bone" chance="34" />
		<item id="behemoth claw" chance="32" />
		<item id="crowbar" chance="16" />
		<item id="amphora" chance="11" />
		<item id="war axe" chance="2" />
		<item id="gold coin" chance="2271" countmax="120" />
		<item id="platinum coin" chance="1166" countmax="4" />
		<item id="meat" chance="921" />
		<item id="assassin star" chance="282" countmax="2" />
		<item id="double axe" chance="160" />
		<item id="battle stone" chance="135" />
		<item id="small amethyst" chance="101" countmax="2" />
		<item id="two handed sword" chance="99" />
		<item id="plate armor" chance="96" />
		<item id="dark armor" chance="78" />
		<item id="giant sword" chance="34" />
		<item id="perfect behemoth fang" chance="30" />
		<item id="great health potion" chance="28" />
		<item id="strange symbol" chance="28" />
		<item id="pick" chance="21" />
		<item id="crystal necklace" chance="16" />
		<item id="big bone" chance="14" />
		<item id="behemoth claw" chance="11" />
		<item id="steel boots" chance="11" />
		<item id="crowbar" chance="9" />
		<item id="behemoth trophy" chance="7" />
		<item id="titan axe" chance="7" />
		<item id="amphora" chance="2" />
		<item id="gold coin" chance="30163" countmax="140" />
		<item id="meat" chance="11209" />
		<item id="assassin star" chance="3440" countmax="2" />
		<item id="double axe" chance="2088" />
		<item id="battle stone" chance="1524" />
		<item id="two handed sword" chance="1391" />
		<item id="small amethyst" chance="1386" countmax="2" />
		<item id="dark armor" chance="1125" />
		<item id="crowbar" chance="724" />
		<item id="plate armor" chance="724" />
		<item id="amphora" chance="532" />
		<item id="big bone" chance="493" />
		<item id="pick" chance="474" />
		<item id="platinum coin" chance="371" countmax="4" />
		<item id="giant sword" chance="369" />
		<item id="perfect behemoth fang" chance="360" />
		<item id="great health potion" chance="275" />
		<item id="strange symbol" chance="275" />
		<item id="behemoth claw" chance="186" />
		<item id="steel boots" chance="160" />
		<item id="crystal necklace" chance="99" />
		<item id="titan axe" chance="34" />
		<item id="war axe" chance="30" />
		<item id="behemoth trophy" chance="25" />
	</loot>
</monster>