<?xml version="1.0" encoding="utf-8"?>
<monster name="Demon Skeleton" nameDescription="a demon skeleton" experience="240" speed="180" manacost="620">
	<health now="400" max="400" />
	<look type="37" head="0" body="0" legs="0" feet="0" addons="0" mount="0" corpse="0" />
	<targetchange interval="2000" chance="0" />
	<flags>
		<flag attackable="1" />
		<flag hostile="1" />
		<flag summonable="1" />
		<flag convinceable="1" />
		<flag illusionable="1" />
		<flag isboss="0" />
		<flag ignorespawnblock="1" />
		<flag pushable="0" />
		<flag canpushitems="1" />
		<flag canpushcreatures="1" />
		<flag staticattack="90" />
		<flag targetdistance="1" />
		<flag healthHidden="0" />
		<flag canWalkOnEnergy="0" />
		<flag canWalkOnFire="1" />
		<flag canWalkOnPoison="1" />
	</flags>
	<immunities>
		<immunity paralyze="1" />
		<immunity outfit="0" />
		<immunity invisible="0" />
		<immunity drunk="0" />
		<immunity bleed="0" />
	</immunities>
	<elements>
		<element physicalPercent="0" />
		<element energyPercent="0" />
		<element earthPercent="100" />
		<element firePercent="100" />
		<element lifedrainPercent="100" />
		<element manadrainPercent="0" />
		<element drownPercent="100" />
		<element icePercent="0" />
		<element holyPercent="-25" />
		<element deathPercent="100" />
	</elements>
	<attacks>
		<attack name="melee" interval="2000" chance="100" min="0" max="-185" />
	</attacks>
	<defenses armor="25" defense="25" />
	<loot>
		<item name="gold coin" chance="97517" countmax="75" />
		<item name="demonic skeletal hand" chance="11974" />
		<item name="throwing star" chance="9990" countmax="3" />
		<item name="health potion" chance="9703" countmax="2" />
		<item name="mana potion" chance="5053" />
		<item name="battle shield" chance="4955" />
		<item name="torch" chance="4868" />
		<item name="battle hammer" chance="4064" />
		<item name="iron helmet" chance="3379" />
		<item name="black pearl" chance="2977" />
		<item name="small ruby" chance="1530" />
		<item name="mysterious fetish" chance="532" />
		<item name="mind stone" chance="469" />
		<item name="guardian shield" chance="112" />
	</loot>
</monster>