<?xml version="1.0" encoding="utf-8"?>
<monster name="Feral Sphinx" nameDescription="a feral sphinx" experience="8800" speed="320" manacost="0">
	<health now="9800" max="9800" />
	<look type="1188" head="76" body="75" legs="57" feet="0" addons="2" mount="0" corpse="0" />
	<targetchange interval="2000" chance="0" />
	<flags>
		<flag attackable="1" />
		<flag hostile="1" />
		<flag summonable="0" />
		<flag convinceable="0" />
		<flag illusionable="0" />
		<flag isboss="0" />
		<flag ignorespawnblock="0" />
		<flag pushable="0" />
		<flag canpushitems="1" />
		<flag canpushcreatures="1" />
		<flag staticattack="90" />
		<flag targetdistance="1" />
		<flag healthhidden="0" />
		<flag canwalkonenergy="1" />
		<flag canwalkonfire="1" />
		<flag canwalkonpoison="1" />
	</flags>
	<immunities>
		<immunity paralyze="1" />
		<immunity outfit="0" />
		<immunity invisible="1" />
		<immunity drunk="1" />
		<immunity bleed="0" />
	</immunities>
	<elements>
		<element physicalPercent="0" />
		<element energyPercent="0" />
		<element earthPercent="0" />
		<element firePercent="0" />
		<element lifedrainPercent="0" />
		<element manadrainPercent="0" />
		<element drownPercent="0" />
		<element icePercent="0" />
		<element holyPercent="0" />
		<element deathPercent="0" />
	</elements>
	<attacks>
		<attack name="melee" interval="2000" chance="100" min="0" max="-450" />
	</attacks>
	<defenses armor="90" defense="90" />
	<voices interval="5000" chance="10">
		<voice sentence="I am not as kind as my sisters!" yell="false" />
	</voices>
	<loot>
		<item id="2152" name="platinum coin" chance="100000" countmax="3" />
		<item id="18419" name="cyan crystal fragment" chance="8036" />
		<item id="2156" name="red gem" chance="7664" />
		<item id="2201" name="dragon necklace" chance="7451" />
		<item id="7890" name="magma amulet" chance="6812" />
		<item id="18415" name="green crystal shard" chance="5907" />
		<item id="34093" name="sphinx feather" chance="5588" />
		<item id="2187" name="wand of inferno" chance="5482" />
		<item id="34094" name="sphinx tiara" chance="4790" />
		<item id="2146" name="small sapphire" chance="4630" countmax="2" />
		<item id="8921" name="wand of draconia" chance="4204" />
		<item id="2432" name="fire axe" chance="3459" />
		<item id="2158" name="blue gem" chance="3353" />
		<item id="7891" name="magma boots" chance="2076" />
		<item id="7900" name="magma monocle" chance="1543" />
		<item id="7894" name="magma legs" chance="1437" />
		<item id="7761" name="small enchanted emerald" chance="1277" countmax="2" />
		<item id="2155" name="green gem" chance="745" />
	</loot>
</monster>