<?xml version="1.0" encoding="utf-8"?>
<monster name="Werefox" nameDescription="a werefox" experience="1600" speed="280" manacost="0">
	<health now="1500" max="1500" />
	<look type="1030" head="0" body="0" legs="0" feet="0" addons="0" mount="0" corpse="0" />
	<targetchange interval="2000" chance="0" />
	<flags>
		<flag attackable="1" />
		<flag hostile="1" />
		<flag summonable="0" />
		<flag convinceable="0" />
		<flag illusionable="0" />
		<flag isboss="0" />
		<flag ignorespawnblock="0" />
		<flag pushable="0" />
		<flag canpushitems="1" />
		<flag canpushcreatures="1" />
		<flag staticattack="90" />
		<flag targetdistance="4" />
		<flag healthHidden="0" />
		<flag canWalkOnEnergy="0" />
		<flag canWalkOnFire="0" />
		<flag canWalkOnPoison="0" />
	</flags>
	<immunities>
		<immunity paralyze="1" />
		<immunity outfit="0" />
		<immunity invisible="1" />
		<immunity drunk="0" />
		<immunity bleed="0" />
	</immunities>
	<elements>
		<element physicalPercent="5" />
		<element energyPercent="10" />
		<element earthPercent="40" />
		<element firePercent="-10" />
		<element lifedrainPercent="0" />
		<element manadrainPercent="0" />
		<element drownPercent="0" />
		<element icePercent="0" />
		<element holyPercent="-10" />
		<element deathPercent="40" />
	</elements>
	<attacks>
		<attack name="melee" interval="2000" chance="100" min="0" max="0" />
	</attacks>
	<defenses armor="35" defense="35" />
	<voices interval="5000" chance="10">
		<voice sentence="Grrrrrr" yell="false" />
		<voice sentence="Yelp!" yell="false" />
	</voices>
	<loot>
		<item name="platinum coin" chance="89929" countmax="4" />
		<item name="gold coin" chance="83952" countmax="85" />
		<item name="fox paw" chance="15299" />
		<item name="werefox tail" chance="13243" />
		<item name="troll green" chance="5123" />
		<item name="mana potion" chance="5053" />
		<item name="strong mana potion" chance="4269" />
		<item name="assassin star" chance="3102" countmax="5" />
		<item name="emerald bangle" chance="2945" />
		<item name="moonlight rod" chance="2056" />
		<item name="great mana potion" chance="1882" />
		<item name="small enchanted emerald" chance="1481" countmax="2" />
		<item name="ring of healing" chance="1115" />
		<item name="werewolf amulet" chance="836" />
		<item name="moonlight crystals" chance="802" />
		<item name="platinum amulet" chance="488" />
		<item name="werefox trophy" chance="139" />
	</loot>
</monster>